report_ranger/__init__.py
report_ranger/config.py
report_ranger/contentassistant.py
report_ranger/default-templates/plain-template/rr-plain-latex.tex
report_ranger/default-templates/plain-template/rr-plain-template.md
report_ranger/default-templates/plain-template/rr-plain-typst.typ
report_ranger/default-templates/sample-template/page-bg.pdf
report_ranger/default-templates/sample-template/page-bg.svg
report_ranger/default-templates/sample-template/report-ranger-logo.svg
report_ranger/default-templates/sample-template/rr-html-template.html
report_ranger/default-templates/sample-template/rr-latex-template.tex
report_ranger/default-templates/sample-template/rr-sample-template.md
report_ranger/default-templates/sample-template/rr-sample-typst.typ
report_ranger/default-templates/sample-template/sectionheading.pdf
report_ranger/default-templates/sample-template/sectionheading.svg
report_ranger/default-templates/sample-template/titlepage.pdf
report_ranger/default-templates/sample-template/titlepage.svg
report_ranger/environment.py
report_ranger/errors.py
report_ranger/helpers.py
report_ranger/imports/imports.py
report_ranger/imports/section.py
report_ranger/imports/vulnerability.py
report_ranger/markdown_renderer/csvrenderer.py
report_ranger/markdown_renderer/latexrenderer.py
report_ranger/markdown_renderer/typstrenderer.py
report_ranger/output_formatter/csvformatter.py
report_ranger/output_formatter/docxformatter.py
report_ranger/output_formatter/htmlformatter.py
report_ranger/output_formatter/latexformatter.py
report_ranger/output_formatter/outputformatter.py
report_ranger/output_formatter/typstformatter.py
report_ranger/report.py
report_ranger/report_ranger.py
report_ranger/riskassessment.py
report_ranger/styles.py
report_ranger/table.py
report_ranger/template.py
report_ranger/templatemapper.py
report_ranger/utils/jinja_helpers.py
report_ranger/utils/mdread.py
report_ranger/validation.py
report_ranger/watcher.py
report_ranger-3.3.3.dist-info/METADATA
report_ranger-3.3.3.dist-info/WHEEL
report_ranger-3.3.3.dist-info/entry_points.txt
report_ranger-3.3.3.dist-info/RECORD
