Metadata-Version: 2.1
Name: Report-Ranger
Version: 3.3.3
Summary: Create a report using markdown files.
Home-page: https://gitlab.com/volkis/report-ranger/
License: MIT
Author: Matthew Strahan
Author-email: matt@volkis.com.au
Requires-Python: >=3.10,<4.0
Classifier: License :: OSI Approved :: MIT License
Classifier: Programming Language :: Python :: 3
Classifier: Programming Language :: Python :: 3.10
Classifier: Programming Language :: Python :: 3.11
Classifier: Programming Language :: Python :: 3.12
Requires-Dist: argparse
Requires-Dist: cerberus
Requires-Dist: jinja2
Requires-Dist: kaleido (==0.2.1)
Requires-Dist: mistune
Requires-Dist: num2words
Requires-Dist: numpy
Requires-Dist: openpyxl
Requires-Dist: pandas
Requires-Dist: platformdirs
Requires-Dist: plotly
Requires-Dist: pyyaml
Requires-Dist: tabulate
Requires-Dist: watchdog
Project-URL: Documentation, https://gitlab.com/volkis/report-ranger/-/wikis/home
Project-URL: Repository, https://gitlab.com/volkis/report-ranger/
